musicautobot/__init__.py
musicautobot/config.py
musicautobot/numpy_encode.py
musicautobot/vocab.py
musicautobot/multitask_transformer/__init__.py
musicautobot/multitask_transformer/dataloader.py
musicautobot/multitask_transformer/learner.py
musicautobot/multitask_transformer/model.py
musicautobot/multitask_transformer/transform.py
musicautobot/music_transformer/__init__.py
musicautobot/music_transformer/dataloader.py
musicautobot/music_transformer/learner.py
musicautobot/music_transformer/model.py
musicautobot/music_transformer/transform.py
musicautobot/utils/__init__.py
musicautobot/utils/attention_mask.py
musicautobot/utils/file_processing.py
musicautobot/utils/lamb.py
musicautobot/utils/midifile.py
musicautobot/utils/setup_musescore.py
musicautobot/utils/stacked_dataloader.py
musicautobot/utils/top_k_top_p.py
musicautobot-0.0.1.dist-info/LICENSE
musicautobot-0.0.1.dist-info/METADATA
musicautobot-0.0.1.dist-info/WHEEL
musicautobot-0.0.1.dist-info/top_level.txt
musicautobot-0.0.1.dist-info/RECORD
