Metadata-Version: 2.1
Name: musicautobot
Version: 0.0.1
Summary: Library for preprocessing MIDI files used in machine learning
Home-page: https://github.com/XsongyangX/musicautobot
Author: Song Yang
Author-email: songyang1218@gmail.com
License: UNKNOWN
Project-URL: Bug Tracker, https://github.com/XsongyangX/musicautobot/issues
Platform: UNKNOWN
Classifier: Programming Language :: Python :: 3
Classifier: License :: OSI Approved :: MIT License
Classifier: Operating System :: OS Independent
Requires-Python: >=3.6
